glia_test_mods/__init__.py
glia_test_mods/mod/glia__glia_test_mods__Kir2_3__0.mod
glia_test_mods/mod/glia__glia_test_mods__cdp5__CR.mod
glia_test_mods-0.0.3.data/data/mod/glia__glia_test_mods__Kir2_3__0.mod
glia_test_mods-0.0.3.data/data/mod/glia__glia_test_mods__cdp5__CR.mod
glia_test_mods-0.0.3.dist-info/METADATA
glia_test_mods-0.0.3.dist-info/WHEEL
glia_test_mods-0.0.3.dist-info/entry_points.txt
glia_test_mods-0.0.3.dist-info/top_level.txt
glia_test_mods-0.0.3.dist-info/RECORD
