Metadata-Version: 2.1
Name: glia-test-mods
Version: 0.0.3
Summary: Glia package of NEURON models
Home-page: https://github.com/dbbs-lab/glia
Author: Robin De Schepper
Author-email: robingilbert.deschepper@unipv.it
License: GPLv3
Platform: UNKNOWN
Classifier: Programming Language :: Python :: 3
Classifier: Operating System :: OS Independent
Requires-Dist: nrn-glia (>=0.1.1)
